rxn_network/__init__.py
rxn_network/core.py
rxn_network/py.typed
rxn_network/costs/__init__.py
rxn_network/costs/base.py
rxn_network/costs/calculators.py
rxn_network/costs/functions.py
rxn_network/costs/pareto.py
rxn_network/data/README.md
rxn_network/data/__init__.py
rxn_network/data/available_precursors.json
rxn_network/data/common_gases.json
rxn_network/data/fit_carbonate_correction.ipynb
rxn_network/data/mu_elements.json
rxn_network/data/freed/compounds.json.gz
rxn_network/data/nist/JANAF_index.txt
rxn_network/data/nist/compounds.json.gz
rxn_network/data/nist/deprecated_compounds.json
rxn_network/data/nist/ignore_solids.json
rxn_network/entries/__init__.py
rxn_network/entries/corrections.py
rxn_network/entries/entry_set.py
rxn_network/entries/experimental.py
rxn_network/entries/freed.py
rxn_network/entries/gibbs.py
rxn_network/entries/interpolated.py
rxn_network/entries/nist.py
rxn_network/entries/utils.py
rxn_network/enumerators/__init__.py
rxn_network/enumerators/base.py
rxn_network/enumerators/basic.py
rxn_network/enumerators/minimize.py
rxn_network/enumerators/utils.py
rxn_network/flows/__init__.py
rxn_network/flows/core.py
rxn_network/jobs/__init__.py
rxn_network/jobs/core.py
rxn_network/jobs/schema.py
rxn_network/jobs/utils.py
rxn_network/network/__init__.py
rxn_network/network/base.py
rxn_network/network/entry.py
rxn_network/network/network.py
rxn_network/network/visualize.py
rxn_network/pathways/__init__.py
rxn_network/pathways/balanced.py
rxn_network/pathways/base.py
rxn_network/pathways/basic.py
rxn_network/pathways/pathway_set.py
rxn_network/pathways/plotting.py
rxn_network/pathways/solver.py
rxn_network/reactions/__init__.py
rxn_network/reactions/base.py
rxn_network/reactions/basic.py
rxn_network/reactions/computed.py
rxn_network/reactions/hull.py
rxn_network/reactions/open.py
rxn_network/reactions/plotting.py
rxn_network/reactions/reaction_set.py
rxn_network/thermo/__init__.py
rxn_network/thermo/chempot_diagram.py
rxn_network/thermo/utils.py
reaction_network-8.3.0.dist-info/LICENSE
reaction_network-8.3.0.dist-info/METADATA
reaction_network-8.3.0.dist-info/WHEEL
reaction_network-8.3.0.dist-info/top_level.txt
reaction_network-8.3.0.dist-info/RECORD
