Metadata-Version: 2.1
Name: reaction-network
Version: 8.3.0
Summary: Reaction-network is a Python package for synthesis planning and predicting chemical reaction pathways in inorganic materials synthesis.
Author-email: Matthew McDermott <mcdermott@lbl.gov>
License: modified BSD
Project-URL: homepage, https://materialsproject.github.io/reaction-network/
Project-URL: documentation, https://materialsproject.github.io/reaction-network/
Project-URL: repository, https://github.com/materialsproject/reaction-network
Project-URL: changelog, https://github.com/materialsproject/reaction-network/blob/main/docs/CHANGELOG.md
Keywords: reaction,network,computational,graph,inorganic,materials,retrosynthesis,synthesis,planning
Classifier: Programming Language :: Python :: 3
Classifier: Programming Language :: Python :: 3.9
Classifier: Programming Language :: Python :: 3.10
Classifier: Programming Language :: Python :: 3.11
Classifier: Intended Audience :: Science/Research
Classifier: License :: OSI Approved :: BSD License
Classifier: Operating System :: OS Independent
Classifier: Topic :: Scientific/Engineering :: Information Analysis
Classifier: Topic :: Scientific/Engineering :: Physics
Classifier: Topic :: Scientific/Engineering :: Chemistry
Classifier: Topic :: Software Development :: Libraries :: Python Modules
Requires-Python: >=3.9
License-File: LICENSE
Requires-Dist: pymatgen >=2023.11.12
Requires-Dist: numba >=0.58.1
Requires-Dist: jobflow >=0.1.15
Requires-Dist: ray >=2.9.0
Requires-Dist: rustworkx >=0.13.2
Provides-Extra: docs
Requires-Dist: autodoc-pydantic ==2.0.1 ; extra == 'docs'
Requires-Dist: furo ==2023.9.10 ; extra == 'docs'
Requires-Dist: ipython ==8.16.1 ; extra == 'docs'
Requires-Dist: myst-parser ==2.0.0 ; extra == 'docs'
Requires-Dist: nbsphinx ==0.9.3 ; extra == 'docs'
Requires-Dist: sphinx-copybutton ==0.5.2 ; extra == 'docs'
Requires-Dist: sphinx ==7.2.6 ; extra == 'docs'
Provides-Extra: strict
Requires-Dist: pymatgen ==2023.12.18 ; extra == 'strict'
Requires-Dist: numba ==0.58.1 ; extra == 'strict'
Requires-Dist: jobflow ==0.1.15 ; extra == 'strict'
Requires-Dist: ray ==2.9.0 ; extra == 'strict'
Requires-Dist: rustworkx ==0.13.2 ; extra == 'strict'
Provides-Extra: tests
Requires-Dist: mp-api ==0.39.4 ; extra == 'tests'
Requires-Dist: pytest ==7.4.3 ; extra == 'tests'
Requires-Dist: pytest-cov ==4.1.0 ; extra == 'tests'
Requires-Dist: pytest-xdist ==3.5.0 ; extra == 'tests'
